<?xml version="1.0" encoding="utf-8" ?>
<dwsync>
<file name="Chemically modified graphene films with tunable negative Poisson’s ratios.pdf" server="210.42.122.166" local="132050426087676288" remote="132050432400000000" Dst="0" />
<file name="Bio-inspired graphene-derived membranes with.pdf" server="210.42.122.166" local="131955694330000000" remote="132073913400000000" Dst="0" />
<file name="Adhesion Energy of MoS2 Thin Films on Silicon-Based Substrates.pdf" server="210.42.122.166" local="131955694330000000" remote="132073915200000000" Dst="0" />
<file name="Controlled Growth of Single-Crystal Twelve-Pointed Graphene Grains on a Liquid Cu Surface.pdf" server="210.42.122.166" local="131955694330000000" remote="132073913400000000" Dst="0" />
<file name="Degradation and recovery of graphene polymer interfaces under cyclic.pdf" server="210.42.122.166" local="131955694330000000" remote="132073913400000000" Dst="0" />
<file name="Confined, Oriented, and Electrically.pdf" server="210.42.122.166" local="131955694330000000" remote="132073913400000000" Dst="0" />
<file name="Facile growth of vertically-aligned graphene nanosheets via thermal.pdf" server="210.42.122.166" local="131955694330000000" remote="132073913400000000" Dst="0" />
<file name="Etching-Controlled Growth of Graphene by Chemical Vapor.pdf" server="210.42.122.166" local="131955694330000000" remote="132073913400000000" Dst="0" />
<file name="Hierarchical-structure-dependent high ductility of electrospun.pdf" server="210.42.122.166" local="131955694330000000" remote="132073913400000000" Dst="0" />
<file name="Carbonized Silk Fabric for Ultrastretchable, Highly.pdf" server="210.42.122.166" local="131955694330000000" remote="132073913400000000" Dst="0" />
<file name="Harvesting electrical energy from.pdf" server="210.42.122.166" local="131955694330000000" remote="132073913400000000" Dst="0" />
<file name="Intrinsic mechanical properties of graphene oxide films Strain.pdf" server="210.42.122.166" local="131955694330000000" remote="132073913400000000" Dst="0" />
<file name="Interfacial failure boosts mechanical energy dissipation in carbon nanotube films under ballistic impact.pdf" server="210.42.122.166" local="131955694330000000" remote="132073913400000000" Dst="0" />
<file name="Mechanics of network materials with responsive crosslinks.pdf" server="210.42.122.166" local="131955694330000000" remote="132073913400000000" Dst="0" />
<file name="Mechanical exfoliation of two dimensional materials.pdf" server="210.42.122.166" local="131955694330000000" remote="132073913400000000" Dst="0" />
<file name="Molecular channel driven actuator with.pdf" server="210.42.122.166" local="131955694330000000" remote="132073913400000000" Dst="0" />
<file name="Rollerball-Pen-Drawing Technology for Extremely Foldable.pdf" server="210.42.122.166" local="131955694330000000" remote="132073913400000000" Dst="0" />
<file name="Optimizing Interfacial Cross-Linking in Graphene-Derived Materials,.pdf" server="210.42.122.166" local="131955694330000000" remote="132073913400000000" Dst="0" />
<file name="Strength loss of carbon nanotube fibers explained in a three-level hierarchical model.pdf" server="210.42.122.166" local="131955694330000000" remote="132073913400000000" Dst="0" />
<file name="Large-Area Growth of Five-Lobed and Triangular Graphene.pdf" server="210.42.122.166" local="131955694330000000" remote="132073913400000000" Dst="0" />
<file name="Thin-Shell Thickness of.pdf" server="210.42.122.166" local="131955694330000000" remote="132073913400000000" Dst="0" />
<file name="Rolling up Transition Metal Dichalcogenide Nanoscrolls via One Drop of Ethanol.pdf" server="210.42.122.166" local="131955694330000000" remote="132073913400000000" Dst="0" />
<file name="Two-dimensional silicaStructural mechanical properties.pdf" server="210.42.122.166" local="131955694330000000" remote="132073913400000000" Dst="0" />
<file name="Transition of Graphene Oxide from Nanomembrane to Nanoscroll.pdf" server="210.42.122.166" local="131955694330000000" remote="132073913400000000" Dst="0" />
<file name="Superflexible C68-graphyne as a promising anode.pdf" server="210.42.122.166" local="132073904693637347" remote="132073916400000000" Dst="0" />
<file name="Microstructural ordering of nanofibers in flow-directed assembly.pdf" server="210.42.122.166" local="132073927714438539" remote="132073928400000000" Dst="0" />
<file name="Sheath-run artificial muscles.pdf" server="210.42.122.166" local="132073919924588816" remote="132073923000000000" Dst="0" />
</dwsync>